<?xml version="1.0" encoding="UTF-8" ?>
<NotepadPlus>
    <Session activeView="0">
        <mainView activeIndex="9">
            <File firstVisibleLine="0" xOffset="0" scrollWidth="3083" startPos="458" endPos="458" selMode="0" offset="0" wrapCount="1" lang="PHP" encoding="-1" userReadOnly="no" filename="\\htp_ds418\web\dolibarr_test\htdocs\custom\smsandroid\core\modules\modSmsandroid.class.php" backupFilePath="" originalFileLastModifTimestamp="864179835" originalFileLastModifTimestampHigh="31258417" mapFirstVisibleDisplayLine="-1" mapFirstVisibleDocLine="-1" mapLastVisibleDocLine="-1" mapNbLine="-1" mapHigherPos="-1" mapWidth="-1" mapHeight="-1" mapKByteInDoc="577044480" mapWrapIndentMode="-1" mapIsWrap="no" />
            <File firstVisibleLine="0" xOffset="0" scrollWidth="3174" startPos="372" endPos="372" selMode="0" offset="0" wrapCount="1" lang="Normal Texte" encoding="-1" userReadOnly="no" filename="\\htp_ds418\web\dolibarr_test\htdocs\custom\smsandroid\langs\fr_FR\smsandroid.lang" backupFilePath="" originalFileLastModifTimestamp="1117942976" originalFileLastModifTimestampHigh="31258600" mapFirstVisibleDisplayLine="-1" mapFirstVisibleDocLine="-1" mapLastVisibleDocLine="-1" mapNbLine="-1" mapHigherPos="-1" mapWidth="-1" mapHeight="-1" mapKByteInDoc="0" mapWrapIndentMode="-1" mapIsWrap="no" />
            <File firstVisibleLine="0" xOffset="0" scrollWidth="1851" startPos="330" endPos="330" selMode="0" offset="0" wrapCount="1" lang="PHP" encoding="-1" userReadOnly="no" filename="\\htp_ds418\web\dolibarr_test\htdocs\custom\smsandroid\admin\setup.php" backupFilePath="" originalFileLastModifTimestamp="-1086126876" originalFileLastModifTimestampHigh="31258616" mapFirstVisibleDisplayLine="-1" mapFirstVisibleDocLine="-1" mapLastVisibleDocLine="-1" mapNbLine="-1" mapHigherPos="-1" mapWidth="-1" mapHeight="-1" mapKByteInDoc="0" mapWrapIndentMode="-1" mapIsWrap="no" />
            <File firstVisibleLine="0" xOffset="0" scrollWidth="2283" startPos="1428" endPos="1428" selMode="0" offset="0" wrapCount="1" lang="PHP" encoding="-1" userReadOnly="no" filename="\\htp_ds418\web\dolibarr_test\htdocs\custom\smsandroid\admin\about.php" backupFilePath="" originalFileLastModifTimestamp="-1019852625" originalFileLastModifTimestampHigh="31258616" mapFirstVisibleDisplayLine="-1" mapFirstVisibleDocLine="-1" mapLastVisibleDocLine="-1" mapNbLine="-1" mapHigherPos="-1" mapWidth="-1" mapHeight="-1" mapKByteInDoc="2507" mapWrapIndentMode="-1" mapIsWrap="no" />
            <File firstVisibleLine="0" xOffset="0" scrollWidth="1379" startPos="241" endPos="241" selMode="0" offset="0" wrapCount="1" lang="PHP" encoding="-1" userReadOnly="no" filename="\\htp_ds418\web\dolibarr_test\htdocs\custom\smsandroid\smsandroidindex.php" backupFilePath="" originalFileLastModifTimestamp="-1054998592" originalFileLastModifTimestampHigh="31258616" mapFirstVisibleDisplayLine="-1" mapFirstVisibleDocLine="-1" mapLastVisibleDocLine="-1" mapNbLine="-1" mapHigherPos="-1" mapWidth="-1" mapHeight="-1" mapKByteInDoc="0" mapWrapIndentMode="-1" mapIsWrap="no" />
            <File firstVisibleLine="0" xOffset="0" scrollWidth="1603" startPos="723" endPos="723" selMode="0" offset="0" wrapCount="1" lang="PHP" encoding="-1" userReadOnly="no" filename="\\htp_ds418\web\dolibarr_test\htdocs\custom\smsandroid\lib\smsandroid.lib.php" backupFilePath="" originalFileLastModifTimestamp="2081527358" originalFileLastModifTimestampHigh="31258606" mapFirstVisibleDisplayLine="-1" mapFirstVisibleDocLine="-1" mapLastVisibleDocLine="-1" mapNbLine="-1" mapHigherPos="-1" mapWidth="-1" mapHeight="-1" mapKByteInDoc="0" mapWrapIndentMode="-1" mapIsWrap="no" />
            <File firstVisibleLine="0" xOffset="0" scrollWidth="1499" startPos="716" endPos="716" selMode="0" offset="0" wrapCount="1" lang="Normal Texte" encoding="-1" userReadOnly="no" filename="\\htp_ds418\web\dolibarr_test\htdocs\custom\smsandroid\langs\en_US\smsandroid.lang" backupFilePath="" originalFileLastModifTimestamp="1133363267" originalFileLastModifTimestampHigh="31258600" mapFirstVisibleDisplayLine="-1" mapFirstVisibleDocLine="-1" mapLastVisibleDocLine="-1" mapNbLine="-1" mapHigherPos="-1" mapWidth="-1" mapHeight="-1" mapKByteInDoc="0" mapWrapIndentMode="-1" mapIsWrap="no" />
            <File firstVisibleLine="0" xOffset="0" scrollWidth="1219" startPos="1126" endPos="1126" selMode="0" offset="0" wrapCount="1" lang="PHP" encoding="-1" userReadOnly="no" filename="\\htp_ds418\web\dolibarr_test\htdocs\custom\smsandroid\ajax\getphone.php" backupFilePath="" originalFileLastModifTimestamp="-1265471804" originalFileLastModifTimestampHigh="31258616" mapFirstVisibleDisplayLine="-1" mapFirstVisibleDocLine="-1" mapLastVisibleDocLine="-1" mapNbLine="-1" mapHigherPos="-1" mapWidth="-1" mapHeight="-1" mapKByteInDoc="7209018" mapWrapIndentMode="-1" mapIsWrap="no" />
            <File firstVisibleLine="0" xOffset="0" scrollWidth="691" startPos="0" endPos="0" selMode="0" offset="0" wrapCount="1" lang="SQL" encoding="-1" userReadOnly="no" filename="\\htp_ds418\web\dolibarr_test\htdocs\custom\smsandroid\sql\dolibarr_allversions.sql" backupFilePath="" originalFileLastModifTimestamp="1821286069" originalFileLastModifTimestampHigh="31255990" mapFirstVisibleDisplayLine="-1" mapFirstVisibleDocLine="-1" mapLastVisibleDocLine="-1" mapNbLine="-1" mapHigherPos="-1" mapWidth="-1" mapHeight="-1" mapKByteInDoc="0" mapWrapIndentMode="-1" mapIsWrap="no" />
            <File firstVisibleLine="0" xOffset="0" scrollWidth="771" startPos="0" endPos="0" selMode="0" offset="0" wrapCount="1" lang="SQL" encoding="-1" userReadOnly="no" filename="\\htp_ds418\web\dolibarr_test\htdocs\custom\smsandroid\sql\llx_smsandroid_log.sql" backupFilePath="" originalFileLastModifTimestamp="2050842691" originalFileLastModifTimestampHigh="31256026" mapFirstVisibleDisplayLine="-1" mapFirstVisibleDocLine="-1" mapLastVisibleDocLine="-1" mapNbLine="-1" mapHigherPos="-1" mapWidth="-1" mapHeight="-1" mapKByteInDoc="1925115648" mapWrapIndentMode="-1" mapIsWrap="no" />
        </mainView>
        <subView activeIndex="0" />
    </Session>
</NotepadPlus>
